{
  "match": false, 
  "people": [
    {
      "face_keypoints": [], 
      "hand_left_keypoints": [], 
      "hand_right_keypoints": [], 
      "pose_keypoints": [
        271.263, 
        326.123, 
        0.830953, 
        273.938, 
        386.087, 
        0.935339, 
        221.823, 
        396.516, 
        0.837667, 
        216.388, 
        482.552, 
        0.870821, 
        203.468, 
        558.241, 
        0.878969, 
        320.817, 
        380.871, 
        0.895533, 
        380.809, 
        320.839, 
        0.875928, 
        427.745, 
        260.761, 
        0.939494, 
        242.666, 
        555.629, 
        0.754683, 
        239.989, 
        678.255, 
        0.862978, 
        234.814, 
        780.063, 
        0.882532, 
        305.282, 
        553.039, 
        0.75897, 
        305.283, 
        675.569, 
        0.809195, 
        302.519, 
        761.854, 
        0.882014, 
        260.749, 
        320.912, 
        0.995697, 
        281.689, 
        320.885, 
        0.968124, 
        242.708, 
        331.317, 
        0.829941, 
        300.099, 
        333.879, 
        1.00683
      ]
    }
  ], 
  "version": 1.0
}