{
  "match": false, 
  "people": [
    {
      "face_keypoints": [], 
      "hand_left_keypoints": [], 
      "hand_right_keypoints": [], 
      "pose_keypoints": [
        583.433, 
        367.07, 
        0.894354, 
        591.615, 
        449.169, 
        0.889772, 
        517.744, 
        446.386, 
        0.837549, 
        427.376, 
        449.271, 
        0.901643, 
        337.014, 
        449.338, 
        0.931229, 
        665.467, 
        457.403, 
        0.818551, 
        682.025, 
        561.588, 
        0.836492, 
        649.263, 
        651.945, 
        0.789725, 
        528.656, 
        651.895, 
        0.719631, 
        533.998, 
        799.773, 
        0.84074, 
        523.18, 
        917.634, 
        0.783823, 
        610.836, 
        662.878, 
        0.699789, 
        602.572, 
        799.801, 
        0.871618, 
        599.744, 
        928.495, 
        0.843689, 
        575.214, 
        358.698, 
        0.937396, 
        599.995, 
        358.727, 
        0.969107, 
        556.143, 
        361.638, 
        0.769749, 
        624.609, 
        364.254, 
        0.93278
      ]
    }
  ], 
  "version": 1.0
}